uw_restclients_sws-2.4.18.dist-info/licenses/LICENSE
uw_sws/VERSION
uw_sws/__init__.py
uw_sws/adviser.py
uw_sws/campus.py
uw_sws/college.py
uw_sws/compat.py
uw_sws/course.py
uw_sws/curriculum.py
uw_sws/dao.py
uw_sws/degree.py
uw_sws/department.py
uw_sws/enrollment.py
uw_sws/exceptions.py
uw_sws/financial.py
uw_sws/models.py
uw_sws/notice.py
uw_sws/person.py
uw_sws/registration.py
uw_sws/section.py
uw_sws/section_status.py
uw_sws/term.py
uw_sws/term_util.py
uw_sws/test.py
uw_sws/thread.py
uw_sws/util.py
uw_sws/resources/sws/file/student/index.html
uw_sws/resources/sws/file/student/just_test.xhtml
uw_sws/resources/sws/file/student/v4/campus.json
uw_sws/resources/sws/file/student/v4/college.json
uw_sws/resources/sws/file/student/v4/curriculum.json_department_abbreviation_EDUC_future_terms_0
uw_sws/resources/sws/file/student/v4/curriculum.json_quarter_winter_year_2013
uw_sws/resources/sws/file/student/v4/department.json_college_abbreviation_MED
uw_sws/resources/sws/file/student/v4/registration.json_instructor_reg_id__curriculum_abbreviation_DROP_T_is_active__section_id_A_course_number_100_year_2013_quarter_winter
uw_sws/resources/sws/file/student/v4/registration.json_instructor_reg_id__curriculum_abbreviation_DROP_T_is_active__section_id_B_course_number_100_year_2013_quarter_winter
uw_sws/resources/sws/file/student/v4/registration.json_instructor_reg_id__curriculum_abbreviation_DROP_T_is_active_on_section_id_A_course_number_100_year_2013_quarter_winter
uw_sws/resources/sws/file/student/v4/registration.json_instructor_reg_id__curriculum_abbreviation_DROP_T_is_active_on_section_id_B_course_number_100_year_2013_quarter_winter
uw_sws/resources/sws/file/student/v4/registration.json_reg_id_00000000000000000000000000000001_quarter_autumn_is_active_on_year_2012
uw_sws/resources/sws/file/student/v4/registration.json_reg_id_00000000000000000000000000000001_quarter_autumn_is_active_on_year_2013
uw_sws/resources/sws/file/student/v4/registration.json_reg_id_00000000000000000000000000000001_quarter_spring_is_active_on_year_2013
uw_restclients_sws-2.4.18.dist-info/METADATA
uw_restclients_sws-2.4.18.dist-info/WHEEL
uw_restclients_sws-2.4.18.dist-info/top_level.txt
uw_restclients_sws-2.4.18.dist-info/RECORD
