Metadata-Version: 2.4
Name: UW-RestClients-SWS
Version: 2.4.18
Summary: A library for connecting to the SWS at the University of Washington
Home-page: https://github.com/uw-it-aca/uw-restclients-sws
Author: UW-IT SETS
Author-email: aca-it@uw.edu
License: Apache License, Version 2.0
Classifier: Intended Audience :: Developers
Classifier: License :: OSI Approved :: Apache Software License
Classifier: Operating System :: OS Independent
Classifier: Programming Language :: Python
License-File: LICENSE
Requires-Dist: UW-RestClients-Core
Requires-Dist: UW-RestClients-PWS
Requires-Dist: pytz
Requires-Dist: mock
Dynamic: author
Dynamic: author-email
Dynamic: classifier
Dynamic: description
Dynamic: home-page
Dynamic: license
Dynamic: license-file
Dynamic: requires-dist
Dynamic: summary
